bambou/__init__.py
bambou/config.py
bambou/exceptions.py
bambou/nurest_connection.py
bambou/nurest_fetcher.py
bambou/nurest_login_controller.py
bambou/nurest_modelcontroller.py
bambou/nurest_object.py
bambou/nurest_push_center.py
bambou/nurest_request.py
bambou/nurest_response.py
bambou/nurest_root_object.py
bambou/nurest_session.py
bambou/utils/__init__.py
bambou/utils/decorators.py
bambou/utils/nuremote_attribute.py
bambou/utils/sha1.py
bambou/utils/singleton.py
bambou-3.1.3.dist-info/LICENSE
bambou-3.1.3.dist-info/METADATA
bambou-3.1.3.dist-info/WHEEL
bambou-3.1.3.dist-info/top_level.txt
bambou-3.1.3.dist-info/RECORD
