Metadata-Version: 2.1
Name: bambou
Version: 3.1.3
Summary: REST Library for Nuage Networks
Home-page: https://github.com/nuagenetworks/bambou
Author: Nuage Networks
Author-email: opensource@nuagenetworks.net
License: BSD-3
Platform: UNKNOWN
Classifier: Development Status :: 5 - Production/Stable
Classifier: Topic :: Utilities
Classifier: License :: OSI Approved :: BSD License
Classifier: Environment :: Console
Classifier: Intended Audience :: Developers
Requires-Dist: requests
Requires-Dist: future
